LICENSE_AURA.txt
LICENSE_MIT.txt
MANIFEST.in
README
distribute_setup.py
setup.py
xpa.c
xpa.pyx
lib/PylabBlockingInput.py
lib/__init__.py
lib/astropy_helper.py
lib/displaydev_lite.py
lib/ds9_basic.py
lib/ds9_pyfits.py
lib/ds9_xpa_help.py
lib/parse_xpahtml.py
lib/pyfits2string.py
lib/verbose.py
lib/version.py
lib/xpa_wrap.py
pysao.egg-info/PKG-INFO
pysao.egg-info/SOURCES.txt
pysao.egg-info/dependency_links.txt
pysao.egg-info/top_level.txt
xpa-2.1.14/COPYING
xpa-2.1.14/Makefile.in
xpa-2.1.14/acl.c
xpa-2.1.14/client.c
xpa-2.1.14/clipboard.c
xpa-2.1.14/command.c
xpa-2.1.14/conf.h.in
xpa-2.1.14/config.guess
xpa-2.1.14/config.sub
xpa-2.1.14/configure
xpa-2.1.14/configure.ac
xpa-2.1.14/find.c
xpa-2.1.14/find.h
xpa-2.1.14/install-sh
xpa-2.1.14/port.c
xpa-2.1.14/prsetup.h
xpa-2.1.14/remote.c
xpa-2.1.14/tcp.c
xpa-2.1.14/tcp.h
xpa-2.1.14/timedconn.c
xpa-2.1.14/timedconn.h
xpa-2.1.14/word.c
xpa-2.1.14/word.h
xpa-2.1.14/xalloc.c
xpa-2.1.14/xalloc.h
xpa-2.1.14/xlaunch.c
xpa-2.1.14/xlaunch.h
xpa-2.1.14/xpa.c
xpa-2.1.14/xpa.h
xpa-2.1.14/xpaio.c
xpa-2.1.14/xpap.h
xpa-2.1.14/xport.h