Metadata-Version: 1.2
Name: pysao
Version: 1.0.2
Summary: python wrapper around SAO XPA and DS9
Home-page: http://github.com/leejjoon/pysao
Author: Jae-Joon Lee
Author-email: lee.j.joon@gmail.com
Maintainer-email: lee.j.joon@gmail.com
License: MIT
Platform: Linux
Platform: Mac OS X
Classifier: Development Status :: 5 - Production/Stable
Classifier: Intended Audience :: Science/Research
Classifier: License :: OSI Approved :: MIT License
Classifier: Operating System :: MacOS :: MacOS X
Classifier: Operating System :: POSIX :: Linux
Classifier: Programming Language :: Cython
Classifier: Programming Language :: Python
Classifier: Programming Language :: Python :: 3
Classifier: Topic :: Scientific/Engineering :: Astronomy
